{
  "fileds": [
    {
      "type": "timestamp",
      "id": "時刻"
    },
    {
      "type": "numeric",
      "id": "水位"
    },
    {
      "type": "text",
      "id": "増減"
    }
  ],
  "records": [
    [
      "23:40",
      "16.32",
      "↑"
    ],
    [
      "23:30",
      "16.31",
      "↑"
    ],
    [
      "23:20",
      "16.3",
      "↑"
    ],
    [
      "23:10",
      "16.29",
      "→"
    ],
    [
      "23:00",
      "16.29",
      "↑"
    ],
    [
      "22:50",
      "16.27",
      "→"
    ]
  ]
}