{
  "fileds": [
    {
      "type": "timestamp",
      "id": "時刻"
    },
    {
      "type": "numeric",
      "id": "水位"
    },
    {
      "type": "text",
      "id": "増減"
    }
  ],
  "records": [
    [
      "15:30",
      "14.99",
      "→"
    ],
    [
      "15:20",
      "14.99",
      "→"
    ],
    [
      "15:10",
      "14.99",
      "↓"
    ],
    [
      "15:00",
      "15",
      "→"
    ],
    [
      "14:50",
      "15",
      "→"
    ],
    [
      "14:40",
      "15",
      "→"
    ]
  ]
}