{
  "fileds": [
    {
      "type": "timestamp",
      "id": "時刻"
    },
    {
      "type": "numeric",
      "id": "水位"
    },
    {
      "type": "text",
      "id": "増減"
    }
  ],
  "records": [
    [
      "20:50",
      "15.1",
      "→"
    ],
    [
      "20:40",
      "15.1",
      "→"
    ],
    [
      "20:30",
      "15.1",
      "→"
    ],
    [
      "20:20",
      "15.1",
      "→"
    ],
    [
      "20:10",
      "15.1",
      "→"
    ],
    [
      "20:00",
      "15.1",
      "↓"
    ]
  ]
}