{
  "fileds": [
    {
      "type": "timestamp",
      "id": "時刻"
    },
    {
      "type": "numeric",
      "id": "水位"
    },
    {
      "type": "text",
      "id": "増減"
    }
  ],
  "records": [
    [
      "02:40",
      "14.6",
      "→"
    ],
    [
      "02:30",
      "14.6",
      "→"
    ],
    [
      "02:20",
      "14.6",
      "→"
    ],
    [
      "02:10",
      "14.6",
      "→"
    ],
    [
      "02:00",
      "14.6",
      "→"
    ],
    [
      "01:50",
      "14.6",
      "→"
    ]
  ]
}