{
  "fileds": [
    {
      "type": "timestamp",
      "id": "時刻"
    },
    {
      "type": "numeric",
      "id": "水位"
    },
    {
      "type": "text",
      "id": "増減"
    }
  ],
  "records": [
    [
      "15:30",
      "15.2",
      "↑"
    ],
    [
      "15:20",
      "15.18",
      "↑"
    ],
    [
      "15:10",
      "15.16",
      "↑"
    ],
    [
      "15:00",
      "15.15",
      "↑"
    ],
    [
      "14:50",
      "15.13",
      "↑"
    ],
    [
      "14:40",
      "15.12",
      "↑"
    ]
  ]
}