{
  "fileds": [
    {
      "type": "timestamp",
      "id": "時刻"
    },
    {
      "type": "numeric",
      "id": "水位"
    },
    {
      "type": "text",
      "id": "増減"
    }
  ],
  "records": [
    [
      "10:20",
      "15.37",
      "↑"
    ],
    [
      "10:10",
      "15.34",
      "↑"
    ],
    [
      "10:00",
      "15.29",
      "↑"
    ],
    [
      "09:50",
      "15.24",
      "↑"
    ],
    [
      "09:40",
      "15.2",
      "↑"
    ],
    [
      "09:30",
      "15.18",
      "↑"
    ]
  ]
}